README.txt
setup.py
OpenPyxlLibrary/OpenPyxlLibrary.py
OpenPyxlLibrary/__init__.py
robotframework_openpyxllib2.egg-info/PKG-INFO
robotframework_openpyxllib2.egg-info/SOURCES.txt
robotframework_openpyxllib2.egg-info/dependency_links.txt
robotframework_openpyxllib2.egg-info/requires.txt
robotframework_openpyxllib2.egg-info/top_level.txt