Metadata-Version: 2.1
Name: robotframework-openpyxllib2
Version: 0.1
Summary: Robotframework library for excel xlsx file format
Home-page: https://github.com/matthewdy/robotframework-openpyxllib
Author: Vallinayagam.K
Author-email: yuemoon2006@hotmail.com
License: UNKNOWN
Platform: UNKNOWN
